<?xml version = '1.0' encoding = 'UTF-8'?>
<Relation class="oracle.dbtools.crest.model.design.logical.Relation" name="Cartav1" directorySegmentName="seg_0" id="B563ADB0-1CEC-EFC6-CDFC-25F4DB1721E9">
<createdBy>orteg</createdBy>
<createdTime>2023-09-27 05:10:11 UTC</createdTime>
<ownerDesignName>dmd</ownerDesignName>
<engineerTo>
<item key="7BA93118-9A88-7FB0-56FD-318C1BA15AF9" value="true"/>
</engineerTo>
<identifying>false</identifying>
<optionalSource>true</optionalSource>
<optionalTarget>false</optionalTarget>
<sourceCardinality>*</sourceCardinality>
<sourceEntity>5F14AF6B-44C5-4CF2-8FFC-B098A4D4FFC1</sourceEntity>
<targetCardinalityString>*</targetCardinalityString>
<targetEntity>DD1FFCC0-DD0A-6C4D-4173-8CC3DC42261B</targetEntity>
<transferable>true</transferable>
<deleteRule>NO ACTION</deleteRule>
</Relation>
