<?xml version = '1.0' encoding = 'UTF-8'?>
<Diagram class="oracle.dbtools.crest.swingui.relational.DPVRelational" name="Relational_1" id="05A5C0F3-EE79-02FB-6047-E402AE5245EB">
<createdBy>pabluchenko</createdBy>
<modifiedBy>pabluchenko</modifiedBy>
<createdTime>2023-09-25 13:56:45 UTC</createdTime>
<autoRoute>false</autoRoute>
<boxInbox>true</boxInbox>
<showLegend>false</showLegend>
<showLabels>false</showLabels>
<showRelAttributes>false</showRelAttributes>
<gridEnabled>false</gridEnabled>
<showGrid>false</showGrid>
<diagramColor>-1</diagramColor>
<display>false</display>
<notation>1</notation>
<objectViews>
<OView class="oracle.dbtools.crest.swingui.relational.TVTable" oid="1CEA7DD0-F7DF-D856-34C8-90565DBCE35E" otype="Table" vid="C2426A06-A947-527D-805E-55EBD7020CD9">
<hideElementsInCurrentOnly>false</hideElementsInCurrentOnly>
<bounds x="195" y="646" width="95" height="70"/>
</OView>
<OView class="oracle.dbtools.crest.swingui.relational.TVTable" oid="1F756BB2-8D82-19A8-00C1-702789B769FF" otype="Table" vid="C09A9AA9-002C-F2C1-275B-C4D1C9AE57CA">
<hideElementsInCurrentOnly>false</hideElementsInCurrentOnly>
<bounds x="1023" y="438" width="91" height="49"/>
</OView>
<OView class="oracle.dbtools.crest.swingui.relational.TVTable" oid="223A9991-BE5A-E99D-9555-B43CC8526BDA" otype="Table" vid="D1DE0A8D-F806-1F80-DFD1-5514CE9C2589">
<hideElementsInCurrentOnly>false</hideElementsInCurrentOnly>
<bounds x="672" y="303" width="170" height="110"/>
</OView>
<OView class="oracle.dbtools.crest.swingui.relational.TVTable" oid="3C3DC533-9A5B-45B1-AD10-629247B0A6BF" otype="Table" vid="2B857B5F-31C3-013B-FEB0-29708EAE60A6">
<hideElementsInCurrentOnly>false</hideElementsInCurrentOnly>
<bounds x="667" y="179" width="170" height="110"/>
</OView>
<OView class="oracle.dbtools.crest.swingui.relational.TVTable" oid="3ECD52D9-3C73-EA2A-6B77-4F5E3F9050F2" otype="Table" vid="1A02E591-1D4B-69A5-384C-38E8168E73CC">
<hideElementsInCurrentOnly>false</hideElementsInCurrentOnly>
<bounds x="1197" y="654" width="101" height="63"/>
</OView>
<OView class="oracle.dbtools.crest.swingui.relational.TVTable" oid="49B773F5-98D2-6B4B-CBB8-2A29CF63FFBC" otype="Table" vid="3E48BFAA-E5F7-D604-29D8-D988B3C5B532">
<hideElementsInCurrentOnly>false</hideElementsInCurrentOnly>
<bounds x="672" y="0" width="228" height="155"/>
</OView>
<OView class="oracle.dbtools.crest.swingui.relational.TVTable" oid="5D2B1AA3-3715-F943-C95B-18C3E464221B" otype="Table" vid="0E724EA4-34E1-9B77-A71F-21559BE201FA">
<hideElementsInCurrentOnly>false</hideElementsInCurrentOnly>
<bounds x="619" y="482" width="261" height="213"/>
</OView>
<OView class="oracle.dbtools.crest.swingui.relational.TVTable" oid="657B1F82-98AC-5627-E531-79290CB72722" otype="Table" vid="123D73D4-5375-2BED-6B20-364BDAFF413E">
<hideElementsInCurrentOnly>false</hideElementsInCurrentOnly>
<bounds x="21" y="116" width="190" height="110"/>
</OView>
<OView class="oracle.dbtools.crest.swingui.relational.TVTable" oid="7101C726-EE5F-2946-3071-97F778A38893" otype="Table" vid="D27565C8-0412-67B8-D411-03B01B432BAB">
<hideElementsInCurrentOnly>false</hideElementsInCurrentOnly>
<bounds x="259" y="409" width="135" height="119"/>
</OView>
<OView class="oracle.dbtools.crest.swingui.relational.TVTable" oid="7B289F3B-EEFB-A174-A25F-954A1ED97D08" otype="Table" vid="E6353827-EC98-E198-E539-05944A874CB2">
<hideElementsInCurrentOnly>false</hideElementsInCurrentOnly>
<bounds x="292" y="6" width="177" height="90"/>
</OView>
<OView class="oracle.dbtools.crest.swingui.relational.TVTable" oid="8136895B-BC04-476F-AF12-138B1F1F3BCD" otype="Table" vid="CFA089AA-E042-4E49-9153-75824925F01D">
<hideElementsInCurrentOnly>false</hideElementsInCurrentOnly>
<bounds x="899" y="367" width="116" height="65"/>
</OView>
<OView class="oracle.dbtools.crest.swingui.relational.TVTable" oid="828544AD-A063-9F20-680A-DCC41E9518E6" otype="Table" vid="952B4CFF-27B2-72D2-7912-79C226B3EE83">
<hideElementsInCurrentOnly>false</hideElementsInCurrentOnly>
<bounds x="1070" y="496" width="88" height="55"/>
</OView>
<OView class="oracle.dbtools.crest.swingui.relational.TVTable" oid="849251EE-3C19-2F59-922D-ADAB7468FD1F" otype="Table" vid="D9ED94CE-5353-D0C4-3010-6F845332FDA1">
<hideElementsInCurrentOnly>false</hideElementsInCurrentOnly>
<bounds x="109" y="530" width="114" height="87"/>
</OView>
<OView class="oracle.dbtools.crest.swingui.relational.TVTable" oid="8BEC5D04-6A90-8FF2-84FC-E11A03122A67" otype="Table" vid="091F20B5-4342-28D4-CA0C-EEFBB411FD71">
<hideElementsInCurrentOnly>false</hideElementsInCurrentOnly>
<bounds x="403" y="332" width="187" height="112"/>
</OView>
<OView class="oracle.dbtools.crest.swingui.relational.TVTable" oid="95550CAC-310C-A599-1F5E-658C13F6CA49" otype="Table" vid="BA3E2067-C193-F466-6994-81803970CC7B">
<hideElementsInCurrentOnly>false</hideElementsInCurrentOnly>
<bounds x="442" y="686" width="92" height="59"/>
</OView>
<OView class="oracle.dbtools.crest.swingui.relational.TVTable" oid="977AA0D5-DEFF-5F6D-36C8-BD97391DE8BB" otype="Table" vid="AA1D12A1-51B3-0FDF-683F-5932FB7DFC5C">
<hideElementsInCurrentOnly>false</hideElementsInCurrentOnly>
<bounds x="427" y="577" width="111" height="78"/>
</OView>
<OView class="oracle.dbtools.crest.swingui.relational.TVTable" oid="9B3B1B42-C650-47F5-42C2-B70928D2955F" otype="Table" vid="945F6C65-2278-A27F-0B99-2EC2036503C8">
<hideElementsInCurrentOnly>false</hideElementsInCurrentOnly>
<bounds x="951" y="635" width="157" height="106"/>
</OView>
<OView class="oracle.dbtools.crest.swingui.relational.TVTable" oid="A5D39B07-39E9-F4DE-10E4-FDDD15527A18" otype="Table" vid="EF10AF1D-0F5E-8EAE-CE0C-7AF3978C2E6D">
<hideElementsInCurrentOnly>false</hideElementsInCurrentOnly>
<bounds x="1128" y="336" width="170" height="110"/>
</OView>
<OView class="oracle.dbtools.crest.swingui.relational.TVTable" oid="DFEDC3AA-D07A-80C9-0B58-4B96A5A6364F" otype="Table" vid="9007230A-1E3D-ED40-C34F-A032843E80CF">
<hideElementsInCurrentOnly>false</hideElementsInCurrentOnly>
<bounds x="997" y="170" width="232" height="135"/>
</OView>
<OView class="oracle.dbtools.crest.swingui.relational.TVTable" oid="F6129813-14E7-8C25-936B-2C51481C5060" otype="Table" vid="05E5C8AE-A61F-3DEC-8D97-EA4DF63B6A27">
<hideElementsInCurrentOnly>false</hideElementsInCurrentOnly>
<bounds x="280" y="130" width="203" height="95"/>
</OView>
</objectViews>
<connectors>
<Connector class="oracle.dbtools.crest.swingui.relational.TVFKRelation" oid="00F2B0AB-478B-21AD-43BD-B397E2C1C40C" otype="FKIndexAssociation" vid_source="1A02E591-1D4B-69A5-384C-38E8168E73CC" vid_target="945F6C65-2278-A27F-0B99-2EC2036503C8">
<hideElementsInCurrentOnly>false</hideElementsInCurrentOnly>
<backgroundColor>-16777216</backgroundColor>
<lineWidth>1</lineWidth>
<points>
<point x="1197" y="685"/>
<point x="1108" y="685"/>
</points>
</Connector>
<Connector class="oracle.dbtools.crest.swingui.relational.TVFKRelation" oid="108685B9-C269-1ACC-A974-A48086D4628B" otype="FKIndexAssociation" vid_source="05E5C8AE-A61F-3DEC-8D97-EA4DF63B6A27" vid_target="2B857B5F-31C3-013B-FEB0-29708EAE60A6">
<hideElementsInCurrentOnly>false</hideElementsInCurrentOnly>
<backgroundColor>-16777216</backgroundColor>
<lineWidth>1</lineWidth>
<points>
<point x="483" y="202"/>
<point x="667" y="202"/>
</points>
</Connector>
<Connector class="oracle.dbtools.crest.swingui.relational.TVFKRelation" oid="163FDE1D-83B3-E8D4-1256-4BAD26483D67" otype="FKIndexAssociation" vid_source="CFA089AA-E042-4E49-9153-75824925F01D" vid_target="EF10AF1D-0F5E-8EAE-CE0C-7AF3978C2E6D">
<hideElementsInCurrentOnly>false</hideElementsInCurrentOnly>
<backgroundColor>-16777216</backgroundColor>
<lineWidth>1</lineWidth>
<points>
<point x="1015" y="399"/>
<point x="1128" y="399"/>
</points>
</Connector>
<Connector class="oracle.dbtools.crest.swingui.relational.TVFKRelation" oid="233155F0-84A0-1EFB-BF81-02486FC8555E" otype="FKIndexAssociation" vid_source="0E724EA4-34E1-9B77-A71F-21559BE201FA" vid_target="AA1D12A1-51B3-0FDF-683F-5932FB7DFC5C">
<hideElementsInCurrentOnly>false</hideElementsInCurrentOnly>
<backgroundColor>-16777216</backgroundColor>
<lineWidth>1</lineWidth>
<points>
<point x="619" y="616"/>
<point x="538" y="616"/>
</points>
</Connector>
<Connector class="oracle.dbtools.crest.swingui.relational.TVFKRelation" oid="3187388B-1BEA-EFB3-BBDC-E6967B9D7E53" otype="FKIndexAssociation" vid_source="0E724EA4-34E1-9B77-A71F-21559BE201FA" vid_target="D1DE0A8D-F806-1F80-DFD1-5514CE9C2589">
<hideElementsInCurrentOnly>false</hideElementsInCurrentOnly>
<backgroundColor>-16777216</backgroundColor>
<lineWidth>1</lineWidth>
<points>
<point x="757" y="482"/>
<point x="757" y="413"/>
</points>
</Connector>
<Connector class="oracle.dbtools.crest.swingui.relational.TVFKRelation" oid="3292B0BA-9995-AC19-05EF-86F05DE1AD97" otype="FKIndexAssociation" vid_source="0E724EA4-34E1-9B77-A71F-21559BE201FA" vid_target="BA3E2067-C193-F466-6994-81803970CC7B">
<hideElementsInCurrentOnly>false</hideElementsInCurrentOnly>
<backgroundColor>-16777216</backgroundColor>
<lineWidth>1</lineWidth>
<points>
<point x="619" y="690"/>
<point x="534" y="690"/>
</points>
</Connector>
<Connector class="oracle.dbtools.crest.swingui.relational.TVFKRelation" oid="498B4AA0-C9C7-5FB7-0566-53B958BCA99F" otype="FKIndexAssociation" vid_source="0E724EA4-34E1-9B77-A71F-21559BE201FA" vid_target="D9ED94CE-5353-D0C4-3010-6F845332FDA1">
<hideElementsInCurrentOnly>false</hideElementsInCurrentOnly>
<backgroundColor>-16777216</backgroundColor>
<lineWidth>1</lineWidth>
<points>
<point x="619" y="573"/>
<point x="223" y="573"/>
</points>
</Connector>
<Connector class="oracle.dbtools.crest.swingui.relational.TVFKRelation" oid="584931BA-6F81-01A4-AC23-B0BBBAB96B65" otype="FKIndexAssociation" vid_source="0E724EA4-34E1-9B77-A71F-21559BE201FA" vid_target="C09A9AA9-002C-F2C1-275B-C4D1C9AE57CA">
<hideElementsInCurrentOnly>false</hideElementsInCurrentOnly>
<backgroundColor>-16777216</backgroundColor>
<lineWidth>1</lineWidth>
<points>
<point x="880" y="484"/>
<point x="1023" y="484"/>
</points>
</Connector>
<Connector class="oracle.dbtools.crest.swingui.relational.TVFKRelation" oid="58873FFD-8098-E3F7-5C54-3A171DA56AB1" otype="FKIndexAssociation" vid_source="E6353827-EC98-E198-E539-05944A874CB2" vid_target="3E48BFAA-E5F7-D604-29D8-D988B3C5B532">
<hideElementsInCurrentOnly>false</hideElementsInCurrentOnly>
<backgroundColor>-16777216</backgroundColor>
<lineWidth>1</lineWidth>
<points>
<point x="469" y="51"/>
<point x="672" y="51"/>
</points>
</Connector>
<Connector class="oracle.dbtools.crest.swingui.relational.TVFKRelation" oid="60E017E7-E443-B3DA-9C79-835106418C6C" otype="FKIndexAssociation" vid_source="0E724EA4-34E1-9B77-A71F-21559BE201FA" vid_target="C2426A06-A947-527D-805E-55EBD7020CD9">
<hideElementsInCurrentOnly>false</hideElementsInCurrentOnly>
<backgroundColor>-16777216</backgroundColor>
<lineWidth>1</lineWidth>
<points>
<point x="619" y="670"/>
<point x="290" y="670"/>
</points>
</Connector>
<Connector class="oracle.dbtools.crest.swingui.relational.TVFKRelation" oid="6BF3B524-A469-0167-245C-7E8CAFDECDDF" otype="FKIndexAssociation" vid_source="123D73D4-5375-2BED-6B20-364BDAFF413E" vid_target="05E5C8AE-A61F-3DEC-8D97-EA4DF63B6A27">
<hideElementsInCurrentOnly>false</hideElementsInCurrentOnly>
<backgroundColor>-16777216</backgroundColor>
<lineWidth>1</lineWidth>
<points>
<point x="211" y="177"/>
<point x="280" y="177"/>
</points>
</Connector>
<Connector class="oracle.dbtools.crest.swingui.relational.TVFKRelation" oid="76114AA2-0EB5-E1B4-C1D5-A067FCC686E2" otype="FKIndexAssociation" vid_source="E6353827-EC98-E198-E539-05944A874CB2" vid_target="05E5C8AE-A61F-3DEC-8D97-EA4DF63B6A27">
<hideElementsInCurrentOnly>false</hideElementsInCurrentOnly>
<backgroundColor>-16777216</backgroundColor>
<lineWidth>1</lineWidth>
<points>
<point x="380" y="96"/>
<point x="380" y="130"/>
</points>
</Connector>
<Connector class="oracle.dbtools.crest.swingui.relational.TVFKRelation" oid="965B6E30-B489-CE5F-1B36-BC9816491039" otype="FKIndexAssociation" vid_source="091F20B5-4342-28D4-CA0C-EEFBB411FD71" vid_target="0E724EA4-34E1-9B77-A71F-21559BE201FA">
<hideElementsInCurrentOnly>false</hideElementsInCurrentOnly>
<backgroundColor>-16777216</backgroundColor>
<lineWidth>1</lineWidth>
<points>
<point x="567" y="444"/>
<point x="619" y="500"/>
</points>
</Connector>
<Connector class="oracle.dbtools.crest.swingui.relational.TVFKRelation" oid="AF497779-EA76-279B-3C87-D9061DB1EC5F" otype="FKIndexAssociation" vid_source="0E724EA4-34E1-9B77-A71F-21559BE201FA" vid_target="952B4CFF-27B2-72D2-7912-79C226B3EE83">
<hideElementsInCurrentOnly>false</hideElementsInCurrentOnly>
<backgroundColor>-16777216</backgroundColor>
<lineWidth>1</lineWidth>
<points>
<point x="880" y="523"/>
<point x="1070" y="523"/>
</points>
</Connector>
<Connector class="oracle.dbtools.crest.swingui.relational.TVFKRelation" oid="C9A087D5-DD85-10AC-64FD-F532FA7E9957" otype="FKIndexAssociation" vid_source="0E724EA4-34E1-9B77-A71F-21559BE201FA" vid_target="D27565C8-0412-67B8-D411-03B01B432BAB">
<hideElementsInCurrentOnly>false</hideElementsInCurrentOnly>
<backgroundColor>-16777216</backgroundColor>
<lineWidth>1</lineWidth>
<points>
<point x="619" y="520"/>
<point x="394" y="520"/>
</points>
</Connector>
<Connector class="oracle.dbtools.crest.swingui.relational.TVFKRelation" oid="D5445FAC-8546-3EEF-00B0-6CDC3A6AF6EA" otype="FKIndexAssociation" vid_source="091F20B5-4342-28D4-CA0C-EEFBB411FD71" vid_target="05E5C8AE-A61F-3DEC-8D97-EA4DF63B6A27">
<hideElementsInCurrentOnly>false</hideElementsInCurrentOnly>
<backgroundColor>-16777216</backgroundColor>
<lineWidth>1</lineWidth>
<points>
<point x="443" y="332"/>
<point x="443" y="225"/>
</points>
</Connector>
<Connector class="oracle.dbtools.crest.swingui.relational.TVFKRelation" oid="DD1BED9E-AC14-C3D0-EACE-114888D41142" otype="FKIndexAssociation" vid_source="9007230A-1E3D-ED40-C34F-A032843E80CF" vid_target="2B857B5F-31C3-013B-FEB0-29708EAE60A6">
<hideElementsInCurrentOnly>false</hideElementsInCurrentOnly>
<backgroundColor>-16777216</backgroundColor>
<lineWidth>1</lineWidth>
<points>
<point x="997" y="234"/>
<point x="837" y="234"/>
</points>
</Connector>
<Connector class="oracle.dbtools.crest.swingui.relational.TVFKRelation" oid="E31213BA-AC0E-CBD1-54D8-7F5FD5AA4064" otype="FKIndexAssociation" vid_source="0E724EA4-34E1-9B77-A71F-21559BE201FA" vid_target="945F6C65-2278-A27F-0B99-2EC2036503C8">
<hideElementsInCurrentOnly>false</hideElementsInCurrentOnly>
<backgroundColor>-16777216</backgroundColor>
<lineWidth>1</lineWidth>
<points>
<point x="880" y="665"/>
<point x="951" y="665"/>
</points>
</Connector>
<Connector class="oracle.dbtools.crest.swingui.relational.TVFKRelation" oid="F1F6E1A9-EC35-101F-EC59-E6B6A228D87C" otype="FKIndexAssociation" vid_source="0E724EA4-34E1-9B77-A71F-21559BE201FA" vid_target="CFA089AA-E042-4E49-9153-75824925F01D">
<hideElementsInCurrentOnly>false</hideElementsInCurrentOnly>
<backgroundColor>-16777216</backgroundColor>
<lineWidth>1</lineWidth>
<points>
<point x="866" y="482"/>
<point x="921" y="432"/>
</points>
</Connector>
<Connector class="oracle.dbtools.crest.swingui.relational.TVFKRelation" oid="F743B6B9-8639-648B-C915-A923F7371273" otype="FKIndexAssociation" vid_source="05E5C8AE-A61F-3DEC-8D97-EA4DF63B6A27" vid_target="D1DE0A8D-F806-1F80-DFD1-5514CE9C2589">
<hideElementsInCurrentOnly>false</hideElementsInCurrentOnly>
<backgroundColor>-16777216</backgroundColor>
<lineWidth>1</lineWidth>
<points>
<point x="480" y="225"/>
<point x="672" y="317"/>
</points>
</Connector>
</connectors>
<arcs>
<Arc class="oracle.dbtools.crest.swingui.relational.TVFKArc" oid="8BA4F21F-4B6D-C9E2-FF81-C604FE3537BD" otype="FKArc" vid="914DD8B4-D2C0-4A33-BBD6-DFA6259D5229">
<hideElementsInCurrentOnly>false</hideElementsInCurrentOnly>
<bounds x="599" y="462" width="301" height="253"/>
</Arc>
</arcs>
</Diagram>
